slidershow_builder/__init__.py
slidershow_builder/__main__.py
slidershow_builder/_lib/convert.py
slidershow_builder/_lib/convert_tools.py
slidershow_builder/_lib/env.py
slidershow_builder/_lib/find_file_recursive.py
slidershow_builder/_lib/process.py
slidershow_builder/templates/skelet.html.template
slidershow_builder/templates/style.css
slidershow_builder-0.5.0.dist-info/METADATA
slidershow_builder-0.5.0.dist-info/WHEEL
slidershow_builder-0.5.0.dist-info/entry_points.txt
slidershow_builder-0.5.0.dist-info/top_level.txt
slidershow_builder-0.5.0.dist-info/RECORD
