Metadata-Version: 2.4
Name: slidershow_builder
Version: 0.5.0
Summary: Slideshow builder
Author-email: Edvard Rejthar <slidershow-builder@edvard.cz>
License: LGPL-3.0-or-later
Requires-Python: >=3.10
Requires-Dist: ezodf
Requires-Dist: mininterface[basic]
Requires-Dist: tqdm
